wyhmcpserver/__init__.py
wyhmcpserver-0.1.0.dist-info/WHEEL
wyhmcpserver-0.1.0.dist-info/entry_points.txt
wyhmcpserver-0.1.0.dist-info/METADATA
wyhmcpserver-0.1.0.dist-info/RECORD
